xiaxinghe/__init__.py
xiaxinghe/libformw6.dll
xiaxinghe/libmenuw6.dll
xiaxinghe/libncursesw6.dll
xiaxinghe/libpanelw6.dll
xiaxinghe/ncursesw6-config
xiaxinghe/sl.exe
xiaxinghe-1.0.0.dist-info/LICENSE
xiaxinghe-1.0.0.dist-info/METADATA
xiaxinghe-1.0.0.dist-info/WHEEL
xiaxinghe-1.0.0.dist-info/top_level.txt
xiaxinghe-1.0.0.dist-info/RECORD
