Metadata-Version: 2.1
Name: xiaxinghe
Version: 1.0.0
Summary: 一个Python库，用于个人娱乐整蛊
Home-page: UNKNOWN
Author: 陈苏恺
License: UNKNOWN
Platform: UNKNOWN
Classifier: Programming Language :: Python :: 3
Classifier: License :: OSI Approved :: MIT License
Classifier: Operating System :: OS Independent
Requires-Python: >=3.6
License-File: LICENSE
Requires-Dist: colorama
Requires-Dist: term2048
Requires-Dist: pyperclip
